README.md
setup.py
crit/__init__.py
crit/exceptions.py
crit/utils.py
crit.egg-info/PKG-INFO
crit.egg-info/SOURCES.txt
crit.egg-info/dependency_links.txt
crit.egg-info/entry_points.txt
crit.egg-info/requires.txt
crit.egg-info/top_level.txt
crit/commands/cli.py
crit/commands/__init__.py
crit/commands/cli.py
crit/config/__init__.py
crit/config/config_module.py
crit/config/host.py
crit/executors/__init__.py
crit/executors/base_executor.py
crit/executors/command_executor.py
crit/executors/template_executor.py
crit/sequences/__init__.py
crit/sequences/sequence.py
example/__init__.py
example/config.py
example/test.py
tests/__init__.py
tests/test_base_executor.py
tests/test_cli.py
tests/test_template_executor.py
tests/helpers/__init__.py
tests/helpers/config.py
tests/helpers/test.py