Metadata-Version: 2.1
Name: crit
Version: 0.1
Summary: Crit: infrastructure as actual code
Home-page: https://github.com/jessielaf/crit
Author: Jessie Liauw A Fong
Author-email: jessielaff@live.nl
License: MIT
Keywords: ansible alternative infrastructure as actual code deployment installing setup
Platform: UNKNOWN
Classifier: Development Status :: 2 - Pre-Alpha
Classifier: Environment :: Console
Classifier: License :: OSI Approved :: MIT License
Classifier: Intended Audience :: Developers
Classifier: Intended Audience :: Information Technology
Classifier: Intended Audience :: System Administrators
Classifier: Programming Language :: Python :: 3.6
Classifier: Programming Language :: Python :: 3.7
Classifier: Topic :: System :: Software Distribution
Classifier: Topic :: System :: Systems Administration
Classifier: Topic :: System :: Installation/Setup
Classifier: Topic :: Utilities
Provides-Extra: docs
